[
 {
  "charts": [],
  "content": "[{\"id\":\"gMDYhsn6Gj\",\"type\":\"number_card\",\"data\":{\"number_card_name\":\"Active Customers\",\"col\":3}},{\"id\":\"rcmAMqnlbW\",\"type\":\"number_card\",\"data\":{\"number_card_name\":\"Total Sales Invoices Bills\",\"col\":3}},{\"id\":\"Ix5o4Xj2sd\",\"type\":\"number_card\",\"data\":{\"number_card_name\":\"Total Sales Payment\",\"col\":3}},{\"id\":\"FGoPbJtZ6l\",\"type\":\"number_card\",\"data\":{\"number_card_name\":\"Total Active Items\",\"col\":3}},{\"id\":\"FiJ_7mxABi\",\"type\":\"number_card\",\"data\":{\"number_card_name\":\"Active Suppliers\",\"col\":3}},{\"id\":\"Ae-5iFEu6C\",\"type\":\"number_card\",\"data\":{\"number_card_name\":\"Total Purchase Invoices Bills\",\"col\":3}},{\"id\":\"SgHYScmvb2\",\"type\":\"number_card\",\"data\":{\"number_card_name\":\"Total Purchase Payment\",\"col\":3}},{\"id\":\"XcfC0kcsMj\",\"type\":\"number_card\",\"data\":{\"number_card_name\":\"Total Stock Value\",\"col\":3}},{\"id\":\"InCkFNkTHe\",\"type\":\"spacer\",\"data\":{\"col\":12}},{\"id\":\"20Epdp8T8D\",\"type\":\"shortcut\",\"data\":{\"shortcut_name\":\"Item\",\"col\":3}},{\"id\":\"bYjT1UqAIK\",\"type\":\"shortcut\",\"data\":{\"shortcut_name\":\"Item Group\",\"col\":3}},{\"id\":\"vRdJa8_Xaw\",\"type\":\"shortcut\",\"data\":{\"shortcut_name\":\"Item Price\",\"col\":3}},{\"id\":\"h4H0NIWA1D\",\"type\":\"shortcut\",\"data\":{\"shortcut_name\":\"Brand\",\"col\":3}},{\"id\":\"AiLQ-lQwuf\",\"type\":\"shortcut\",\"data\":{\"shortcut_name\":\"Customer\",\"col\":3}},{\"id\":\"6iLAULGPFU\",\"type\":\"shortcut\",\"data\":{\"shortcut_name\":\"Supplier\",\"col\":3}},{\"id\":\"Mi-WCQs4tj\",\"type\":\"shortcut\",\"data\":{\"shortcut_name\":\"Address\",\"col\":3}},{\"id\":\"Cgm2eQrstC\",\"type\":\"shortcut\",\"data\":{\"shortcut_name\":\"Contact\",\"col\":3}},{\"id\":\"7s9SqVACn8\",\"type\":\"shortcut\",\"data\":{\"shortcut_name\":\"Terms and Conditions\",\"col\":3}},{\"id\":\"25K3nmAU4H\",\"type\":\"shortcut\",\"data\":{\"shortcut_name\":\"Purchase Invoice\",\"col\":3}},{\"id\":\"ECkz1APTHv\",\"type\":\"shortcut\",\"data\":{\"shortcut_name\":\"Sales Invoice\",\"col\":3}},{\"id\":\"iWTBM_MsBm\",\"type\":\"shortcut\",\"data\":{\"shortcut_name\":\"Payment Entry\",\"col\":3}},{\"id\":\"u1F22Wjc0E\",\"type\":\"shortcut\",\"data\":{\"shortcut_name\":\"Bank\",\"col\":3}},{\"id\":\"I9eW77nT4t\",\"type\":\"shortcut\",\"data\":{\"shortcut_name\":\"Bank Account\",\"col\":3}},{\"id\":\"oJX3dlowMc\",\"type\":\"shortcut\",\"data\":{\"shortcut_name\":\"Journal Entry\",\"col\":3}},{\"id\":\"0642k734gO\",\"type\":\"shortcut\",\"data\":{\"shortcut_name\":\"Product Repair\",\"col\":3}}]",
  "custom_blocks": [],
  "docstatus": 0,
  "doctype": "Workspace",
  "for_user": "",
  "hide_custom": 0,
  "icon": "getting-started",
  "indicator_color": null,
  "is_hidden": 0,
  "label": "Home",
  "links": [],
  "modified": "2025-09-24 20:20:56.503893",
  "module": "Setup",
  "name": "Home",
  "number_cards": [
   {
    "label": "Active Customers",
    "number_card_name": "Active Customers",
    "parent": "Home",
    "parentfield": "number_cards",
    "parenttype": "Workspace"
   },
   {
    "label": "Total Sales Invoices Bills",
    "number_card_name": "Total Outgoing Bills",
    "parent": "Home",
    "parentfield": "number_cards",
    "parenttype": "Workspace"
   },
   {
    "label": "Total Sales Payment",
    "number_card_name": "Total Incoming Payment",
    "parent": "Home",
    "parentfield": "number_cards",
    "parenttype": "Workspace"
   },
   {
    "label": "Total Active Items",
    "number_card_name": "Total Active Items",
    "parent": "Home",
    "parentfield": "number_cards",
    "parenttype": "Workspace"
   },
   {
    "label": "Active Suppliers",
    "number_card_name": "Active Suppliers",
    "parent": "Home",
    "parentfield": "number_cards",
    "parenttype": "Workspace"
   },
   {
    "label": "Total Purchase Invoices Bills",
    "number_card_name": "Total Incoming Bills",
    "parent": "Home",
    "parentfield": "number_cards",
    "parenttype": "Workspace"
   },
   {
    "label": "Total Purchase Payment",
    "number_card_name": "Total Outgoing Payment",
    "parent": "Home",
    "parentfield": "number_cards",
    "parenttype": "Workspace"
   },
   {
    "label": "Total Stock Value",
    "number_card_name": "Total Stock Value",
    "parent": "Home",
    "parentfield": "number_cards",
    "parenttype": "Workspace"
   }
  ],
  "parent_page": "",
  "public": 1,
  "quick_lists": [],
  "restrict_to_domain": "",
  "roles": [],
  "sequence_id": 1.0,
  "shortcuts": [
   {
    "color": "Grey",
    "doc_view": "List",
    "format": null,
    "icon": null,
    "kanban_board": null,
    "label": "Item",
    "link_to": "Item",
    "parent": "Home",
    "parentfield": "shortcuts",
    "parenttype": "Workspace",
    "report_ref_doctype": null,
    "restrict_to_domain": null,
    "stats_filter": "[]",
    "type": "DocType",
    "url": null
   },
   {
    "color": "Grey",
    "doc_view": "List",
    "format": null,
    "icon": null,
    "kanban_board": null,
    "label": "Product Repair",
    "link_to": "Product Repair",
    "parent": "Home",
    "parentfield": "shortcuts",
    "parenttype": "Workspace",
    "report_ref_doctype": null,
    "restrict_to_domain": null,
    "stats_filter": "[]",
    "type": "DocType",
    "url": null
   },
   {
    "color": "Grey",
    "doc_view": "List",
    "format": null,
    "icon": null,
    "kanban_board": null,
    "label": "Customer",
    "link_to": "Customer",
    "parent": "Home",
    "parentfield": "shortcuts",
    "parenttype": "Workspace",
    "report_ref_doctype": null,
    "restrict_to_domain": null,
    "stats_filter": "[]",
    "type": "DocType",
    "url": null
   },
   {
    "color": "Grey",
    "doc_view": "List",
    "format": null,
    "icon": null,
    "kanban_board": null,
    "label": "Journal Entry",
    "link_to": "Journal Entry",
    "parent": "Home",
    "parentfield": "shortcuts",
    "parenttype": "Workspace",
    "report_ref_doctype": null,
    "restrict_to_domain": null,
    "stats_filter": "[]",
    "type": "DocType",
    "url": null
   },
   {
    "color": "Grey",
    "doc_view": "List",
    "format": null,
    "icon": null,
    "kanban_board": null,
    "label": "Item Group",
    "link_to": "Item Group",
    "parent": "Home",
    "parentfield": "shortcuts",
    "parenttype": "Workspace",
    "report_ref_doctype": null,
    "restrict_to_domain": null,
    "stats_filter": "[]",
    "type": "DocType",
    "url": null
   },
   {
    "color": "Grey",
    "doc_view": "List",
    "format": null,
    "icon": null,
    "kanban_board": null,
    "label": "Address",
    "link_to": "Address",
    "parent": "Home",
    "parentfield": "shortcuts",
    "parenttype": "Workspace",
    "report_ref_doctype": null,
    "restrict_to_domain": null,
    "stats_filter": "[]",
    "type": "DocType",
    "url": null
   },
   {
    "color": "Grey",
    "doc_view": "List",
    "format": null,
    "icon": null,
    "kanban_board": null,
    "label": "Item Price",
    "link_to": "Item Price",
    "parent": "Home",
    "parentfield": "shortcuts",
    "parenttype": "Workspace",
    "report_ref_doctype": null,
    "restrict_to_domain": null,
    "stats_filter": "[]",
    "type": "DocType",
    "url": null
   },
   {
    "color": "Grey",
    "doc_view": "List",
    "format": null,
    "icon": null,
    "kanban_board": null,
    "label": "Contact",
    "link_to": "Contact",
    "parent": "Home",
    "parentfield": "shortcuts",
    "parenttype": "Workspace",
    "report_ref_doctype": null,
    "restrict_to_domain": null,
    "stats_filter": "[]",
    "type": "DocType",
    "url": null
   },
   {
    "color": "Grey",
    "doc_view": "List",
    "format": null,
    "icon": null,
    "kanban_board": null,
    "label": "Brand",
    "link_to": "Brand",
    "parent": "Home",
    "parentfield": "shortcuts",
    "parenttype": "Workspace",
    "report_ref_doctype": null,
    "restrict_to_domain": null,
    "stats_filter": "[]",
    "type": "DocType",
    "url": null
   },
   {
    "color": "Grey",
    "doc_view": "List",
    "format": null,
    "icon": null,
    "kanban_board": null,
    "label": "Terms and Conditions",
    "link_to": "Terms and Conditions",
    "parent": "Home",
    "parentfield": "shortcuts",
    "parenttype": "Workspace",
    "report_ref_doctype": null,
    "restrict_to_domain": null,
    "stats_filter": "[]",
    "type": "DocType",
    "url": null
   },
   {
    "color": "Grey",
    "doc_view": "List",
    "format": null,
    "icon": null,
    "kanban_board": null,
    "label": "Purchase Invoice",
    "link_to": "Purchase Invoice",
    "parent": "Home",
    "parentfield": "shortcuts",
    "parenttype": "Workspace",
    "report_ref_doctype": null,
    "restrict_to_domain": null,
    "stats_filter": "[]",
    "type": "DocType",
    "url": null
   },
   {
    "color": "Grey",
    "doc_view": "List",
    "format": null,
    "icon": null,
    "kanban_board": null,
    "label": "Sales Invoice",
    "link_to": "Sales Invoice",
    "parent": "Home",
    "parentfield": "shortcuts",
    "parenttype": "Workspace",
    "report_ref_doctype": null,
    "restrict_to_domain": null,
    "stats_filter": "[]",
    "type": "DocType",
    "url": null
   },
   {
    "color": "Grey",
    "doc_view": "List",
    "format": null,
    "icon": null,
    "kanban_board": null,
    "label": "Supplier",
    "link_to": "Supplier",
    "parent": "Home",
    "parentfield": "shortcuts",
    "parenttype": "Workspace",
    "report_ref_doctype": null,
    "restrict_to_domain": null,
    "stats_filter": "[]",
    "type": "DocType",
    "url": null
   },
   {
    "color": "Grey",
    "doc_view": "List",
    "format": null,
    "icon": null,
    "kanban_board": null,
    "label": "Payment Entry",
    "link_to": "Payment Entry",
    "parent": "Home",
    "parentfield": "shortcuts",
    "parenttype": "Workspace",
    "report_ref_doctype": null,
    "restrict_to_domain": null,
    "stats_filter": "[]",
    "type": "DocType",
    "url": null
   },
   {
    "color": "Grey",
    "doc_view": "List",
    "format": null,
    "icon": null,
    "kanban_board": null,
    "label": "Bank",
    "link_to": "Bank",
    "parent": "Home",
    "parentfield": "shortcuts",
    "parenttype": "Workspace",
    "report_ref_doctype": null,
    "restrict_to_domain": null,
    "stats_filter": "[]",
    "type": "DocType",
    "url": null
   },
   {
    "color": "Grey",
    "doc_view": "List",
    "format": null,
    "icon": null,
    "kanban_board": null,
    "label": "Bank Account",
    "link_to": "Bank Account",
    "parent": "Home",
    "parentfield": "shortcuts",
    "parenttype": "Workspace",
    "report_ref_doctype": null,
    "restrict_to_domain": null,
    "stats_filter": "[]",
    "type": "DocType",
    "url": null
   }
  ],
  "title": "Home"
 },
 {
  "charts": [],
  "content": "[{\"id\":\"0HLC3VFsrn\",\"type\":\"shortcut\",\"data\":{\"shortcut_name\":\"Total Stock Summary\",\"col\":3}}]",
  "custom_blocks": [],
  "docstatus": 0,
  "doctype": "Workspace",
  "for_user": "",
  "hide_custom": 0,
  "icon": "file",
  "indicator_color": "green",
  "is_hidden": 0,
  "label": "Reports",
  "links": [],
  "modified": "2025-09-24 20:06:55.147744",
  "module": null,
  "name": "Reports",
  "number_cards": [],
  "parent_page": "",
  "public": 1,
  "quick_lists": [],
  "restrict_to_domain": null,
  "roles": [],
  "sequence_id": 2.0,
  "shortcuts": [
   {
    "color": "Grey",
    "doc_view": "List",
    "format": null,
    "icon": null,
    "kanban_board": null,
    "label": "Total Stock Summary",
    "link_to": "Total Stock Summary",
    "parent": "Reports",
    "parentfield": "shortcuts",
    "parenttype": "Workspace",
    "report_ref_doctype": "Stock Entry",
    "restrict_to_domain": null,
    "stats_filter": null,
    "type": "Report",
    "url": null
   }
  ],
  "title": "Reports"
 }
]